{
  "solution": "/mntdatalora/src/High-DOF-Arm-Planner/output/report_benchmark/seedset_16782/map2/rrt/pair_04_path.txt",
  "map": "/mntdatalora/src/High-DOF-Arm-Planner/maps/map2.txt",
  "waypoints": 64,
  "dofs": 3,
  "total_cost": 7.746475451624585,
  "max_step_cost": 0.14232847754600042,
  "mean_step_cost": 0.12295992780356486,
  "stats": {
    "vertices_generated": "10",
    "first_solution_time": "7.321e-05",
    "used_fallback": "0",
    "plan_waypoints": "64"
  },
  "outputs": {
    "map_motion_gif": "map_motion.gif",
    "map_final_png": "map_final.png"
  }
}